alibabacloud_rdsai20250507/__init__.py
alibabacloud_rdsai20250507/client.py
alibabacloud_rdsai20250507/models/__init__.py
alibabacloud_rdsai20250507/models/_chat_messages_request.py
alibabacloud_rdsai20250507/models/_chat_messages_response.py
alibabacloud_rdsai20250507/models/_chat_messages_response_body.py
alibabacloud_rdsai20250507/models/_chat_messages_shrink_request.py
alibabacloud_rdsai20250507/models/_chat_messages_task_stop_request.py
alibabacloud_rdsai20250507/models/_chat_messages_task_stop_response.py
alibabacloud_rdsai20250507/models/_chat_messages_task_stop_response_body.py
alibabacloud_rdsai20250507/models/_create_app_instance_request.py
alibabacloud_rdsai20250507/models/_create_app_instance_response.py
alibabacloud_rdsai20250507/models/_create_app_instance_response_body.py
alibabacloud_rdsai20250507/models/_create_app_instance_shrink_request.py
alibabacloud_rdsai20250507/models/_create_custom_agent_request.py
alibabacloud_rdsai20250507/models/_create_custom_agent_response.py
alibabacloud_rdsai20250507/models/_create_custom_agent_response_body.py
alibabacloud_rdsai20250507/models/_create_custom_agent_shrink_request.py
alibabacloud_rdsai20250507/models/_delete_app_instance_request.py
alibabacloud_rdsai20250507/models/_delete_app_instance_response.py
alibabacloud_rdsai20250507/models/_delete_app_instance_response_body.py
alibabacloud_rdsai20250507/models/_delete_custom_agent_request.py
alibabacloud_rdsai20250507/models/_delete_custom_agent_response.py
alibabacloud_rdsai20250507/models/_delete_custom_agent_response_body.py
alibabacloud_rdsai20250507/models/_describe_app_instance_attribute_request.py
alibabacloud_rdsai20250507/models/_describe_app_instance_attribute_response.py
alibabacloud_rdsai20250507/models/_describe_app_instance_attribute_response_body.py
alibabacloud_rdsai20250507/models/_describe_app_instances_request.py
alibabacloud_rdsai20250507/models/_describe_app_instances_response.py
alibabacloud_rdsai20250507-2.1.0.dist-info/LICENSE
alibabacloud_rdsai20250507-2.1.0.dist-info/METADATA
alibabacloud_rdsai20250507-2.1.0.dist-info/WHEEL
alibabacloud_rdsai20250507-2.1.0.dist-info/top_level.txt
alibabacloud_rdsai20250507-2.1.0.dist-info/RECORD
